hitsave/__about__.py
hitsave/__init__.py
hitsave/__main__.py
hitsave/authenticate.py
hitsave/blobstore.py
hitsave/cli.py
hitsave/cloudutils.py
hitsave/codegraph.py
hitsave/config.py
hitsave/console.py
hitsave/decorator.py
hitsave/evalstore.py
hitsave/filesnap.py
hitsave/graph.py
hitsave/session.py
hitsave/support_extra.py
hitsave/support_pil.py
hitsave/support_torch.py
hitsave/symbol.py
hitsave/types.py
hitsave/visualize.py
hitsave/util/__init__.py
hitsave/util/config_file.py
hitsave/util/current.py
hitsave/util/dispatch.py
hitsave/util/misc.py
hitsave/util/ofdict.py
hitsave/util/type_helpers.py
hitsave-0.3.12.dist-info/METADATA
hitsave-0.3.12.dist-info/WHEEL
hitsave-0.3.12.dist-info/entry_points.txt
hitsave-0.3.12.dist-info/licenses/LICENSE.txt
hitsave-0.3.12.dist-info/RECORD
