Metadata-Version: 2.1
Name: hitsave
Version: 0.3.12
Summary: Holistic data caching system.
Project-URL: Homepage, https://hitsave.io
Project-URL: Bug Tracker, https://github.com/hitsave-io/xyz/issues
Project-URL: Documentation, https://docs.hitsave.io
Author-email: "E.W.Ayers" <contact@edayers.com>, George Seabridge <seabo@hitsave.io>
License-Expression: MIT
License-File: LICENSE.txt
Classifier: Operating System :: OS Independent
Classifier: Programming Language :: Python :: 3
Requires-Python: >=3.8
Requires-Dist: aiohttp~=3.8
Requires-Dist: blake3~=0.3.1
Requires-Dist: python-dateutil
Requires-Dist: requests~=2.28
Requires-Dist: rich
Requires-Dist: typer~=0.6.1
Requires-Dist: typing-extensions
